GEMDB/GEMDB.py
GEMDB/__init__.py
GEMDB/loader.py
GEMDB/setting.py
GEMDB-1.0.1.dist-info/LICENSE
GEMDB-1.0.1.dist-info/METADATA
GEMDB-1.0.1.dist-info/WHEEL
GEMDB-1.0.1.dist-info/top_level.txt
GEMDB-1.0.1.dist-info/RECORD
