Metadata-Version: 2.1
Name: GEMDB
Version: 1.0.1
Summary: General Electricity Market DataBase
Home-page: https://github.com/tqh16/GEMDB_Loader
Author: eilab-tqh
Author-email: tqh20@mails.tsinghua.edu.cn
License: UNKNOWN
Project-URL: Bug Tracker, https://github.com/tqh16/GEMDB_Loader/issues
Platform: UNKNOWN
Classifier: Programming Language :: Python :: 3
Classifier: License :: OSI Approved :: MIT License
Classifier: Operating System :: OS Independent
Requires-Python: >=3.7
License-File: LICENSE
